{
  "Brann Bronzebeard": "恐龙大师布莱恩",
  "Titus Rivendare": "提克特斯",
  "Rylak Metalhead": "金属者刃蛇",
  "Balinda Stonehearth": "巴琳达·石火",
  "Sewer Lord": "下水道之主",
  "Monstrous Macaw": "巨嘴鹦鹉",
  "Leeroy the Reckless": "冒失的莉莲",
  "Batty Terrorguard": "蝠翼魔",
  "Forsaken Weaver": "被遗忘的织雾者",
  "Drakkari Enchanter": "达卡基尔附魔师",
  "Blade Collector": "刃收集者",
  "Living Azerite": "活性艾泽里特",
  "Banana Slamma": "香蕉毁灭者",
  "Manasaber": "刃豹",
  "Bile Spitter": "吐雾者",
  "Diremuck Forager": "噬雾觅食者",
  "Pufferquil": "刺刺鹦",
  "Bristlebach": "刺背野猪",
  "Prickly Piper": "尖刺 piper",
  "Twisted Wrathguard": "扭曲复仇守卫",
  "Ashen Corruptor": "灰烬腐化者",
  "Malchezaar, Prince of Dance": "舞者玛洛扎",
  "Consummate Conqueror": "完美征服者",
  "Soul Rewinder": "灵魂回溯者",
  "Laboratory Assistant": "实验室助理",
  "Famished Felbat": "饥饿邪蝙蝠",
  "Handless Forsaken": "无手亡魂",
  "Drustfallen Butcher": "坠落的屠夫",
  "Friendly Geist": "友善鬼魂",
  "Felfire Conjurer": "邪火魔术师",
  "Cataclysmic Harbinger": "大灾变先兆",
  "Sky Admiral Rogers": "天空上将罗杰斯",
  "Brazen Buccaneer": "鲁莽海盗",
  "Leyline Surfacer": "地标冲浪者",
  "Wildfire Elemental": "野火元素",
  "Air Revenant": "空气亡魂",
  "Flaming Enforcer": "烈焰执法者",
  "Ancestral Automaton": "祖先自动机",
  "Kangor's Apprentice": "康格尔的学徒",
  "Auto Assembler": "自动装配器",
  "Lurking Leviathan": "潜伏的利维坦",
  "Hunting Tiger Shark": "猎虎鲨",
  "Goldrinn, the Great Wolf": "大奖狼戈德林",
  "Goldrinn": "戈德林",
  "Sewer Rat": "下水道老鼠",
  "Deadly Spore": "致命孢子",
  "Heroic Underdog": "英雄 underdog",
  "Primitive Painter": "原始画家",
  "Expert Aviator": "王牌飞行员",
  "Magicfin Mycologist": "魔鳍真菌师",
  "Bream Counter": "鲷鱼计数器",
  "Mrglin' Burglar": "鱼人盗贼",
  "Cousin Errgl": "表亲 Errgl",
  "Gem Smuggler": "宝石走私贩",
  "Moon-Bacon Jazzer": "月亮培根爵士",
  "Tarecgosa": "塔雷贡萨",
  "Darkgaze Elder": "暗凝视长老",
  "Earthsong Shaman": "大地之歌萨满",
  "Vinespeaker": "藤蔓之声",
  "Geomagus Roogug": "地质师 Roogug",
  "Eternal Summoner": "永恒召唤师",
  "Sinrunner Blanchy": "辛runner Blanchy",
  "Proud Privateer": "骄傲私掠者",
  "Fire-forged Evoker": "火铸唤醒师",
  "Tranquil Meditative": "宁静冥想者",
  "Mummifier": "木乃伊师",
  "Hired Ritualist": "雇佣仪式师",
  "Living Acres": "生还者",
  "Nightbane, Ignited": "夜之灾祸",
  "Wintergrasp Ghoul": "冬握亡灵",
  "Choral Mrrrglr": "合唱鱼人",
  "DK": "死亡骑士"
}